pyspark_huggingface/__init__.py
pyspark_huggingface/compat/__init__.py
pyspark_huggingface/compat/datasource.py
pyspark_huggingface/huggingface.py
pyspark_huggingface/huggingface_sink.py
pyspark_huggingface/huggingface_source.py
pyspark_huggingface-2.0.0.dist-info/WHEEL
pyspark_huggingface-2.0.0.dist-info/METADATA
pyspark_huggingface-2.0.0.dist-info/RECORD
