Metadata-Version: 2.3
Name: pyspark-huggingface
Version: 2.0.0
Summary: A DataSource for reading and writing HuggingFace Datasets in Spark
Author: allisonwang-db, lhoestq, wengh
Author-email: allisonwang-db <allison.wang@databricks.com>, lhoestq <quentin@huggingface.co>, wengh <wenghy02@gmail.com>
License: Apache License 2.0
Requires-Dist: datasets>=4.0
Requires-Dist: huggingface-hub>=0.34.4
Requires-Dist: pyarrow>=21.0.0
Requires-Python: >=3.9
